compass.py
handin1api.py
su_cs144_projectlibs-0.0.4.dist-info/LICENSE
su_cs144_projectlibs-0.0.4.dist-info/METADATA
su_cs144_projectlibs-0.0.4.dist-info/WHEEL
su_cs144_projectlibs-0.0.4.dist-info/top_level.txt
su_cs144_projectlibs-0.0.4.dist-info/RECORD
